R2SN/__init__.py
R2SN/feature_extraction.py
R2SN/data/MNI152_T1_1mm.nii
R2SN/data/rAAL2_1mm.nii
R2SN/data/rBN_Atlas_246_1mm.nii
R2SN/network_feature/ANTS.exe
R2SN/network_feature/N4BiasFieldCorrection.exe
R2SN/network_feature/Params.yaml
R2SN/network_feature/WarpImageMultiTransform.exe
R2SN/network_feature/__init__.py
R2SN/network_feature/feature_extract.py
R2SN/network_feature/feature_extract_parallel.py
R2SN/network_feature/input_csv.py
R2SN/network_feature/name_sort.py
R2SN/network_feature/network.py
R2SN/network_feature/network_compute.py
R2SN/network_feature/picked_features.txt
R2SN/network_feature/registration_lin.py
R2SN/network_feature/registration_win.py
examples/example_R2SN.py
R2SN-1.1.1.dist-info/LICENSE
R2SN-1.1.1.dist-info/METADATA
R2SN-1.1.1.dist-info/WHEEL
R2SN-1.1.1.dist-info/top_level.txt
R2SN-1.1.1.dist-info/RECORD
