Metadata-Version: 2.1
Name: R2SN
Version: 1.1.1
Summary: description
Home-page: https://github.com/YongLiuLab/R2SN
Author: YangFan
Author-email: 2669742207@qq.com
License: MIT-0
Platform: UNKNOWN
Classifier: Programming Language :: Python :: 3
Classifier: License :: OSI Approved :: MIT License
Classifier: Operating System :: OS Independent
Requires-Python: >=3.6
Requires-Dist: nibabel (>=3.2.1)
Requires-Dist: pyradiomics (>=3.0.1)
Requires-Dist: scipy (>=1.6.2)
Requires-Dist: SimpleITK (>=2.1.1.2)
Requires-Dist: numpy (>=1.21.5)
Requires-Dist: pandas (>=1.2.3)
Requires-Dist: sklearn
